gtui/__init__.py
gtui/callback.py
gtui/executor.py
gtui/task.py
gtui/visualizer.py
gtui/utils/__init__.py
gtui/utils/urwid_scroll.py
gtui/utils/werkzeug_local.py
gtui-0.1.1.dist-info/LICENSE
gtui-0.1.1.dist-info/METADATA
gtui-0.1.1.dist-info/WHEEL
gtui-0.1.1.dist-info/top_level.txt
gtui-0.1.1.dist-info/zip-safe
gtui-0.1.1.dist-info/RECORD
