Metadata-Version: 2.1
Name: gtui
Version: 0.1.1
Summary: Simple Task Scheduler & Executor with Friendly Text User Interface
Home-page: https://github.com/CtheSky/gtui
Author: Tianhong Chu
Author-email: cthesky13@gmail.com
License: UNKNOWN
Keywords: TUI,Command Line Tool,Scheduler
Platform: any
Classifier: Operating System :: OS Independent
Classifier: Intended Audience :: Customer Service
Classifier: Intended Audience :: Developers
Classifier: Topic :: Software Development :: Libraries
Classifier: Topic :: Software Development :: Libraries :: Python Modules
Classifier: Programming Language :: Python
Classifier: Programming Language :: Python :: 3
Classifier: Programming Language :: Python :: 3.4
Classifier: Programming Language :: Python :: 3.5
Classifier: Programming Language :: Python :: 3.6
Classifier: Programming Language :: Python :: 3.7
Requires-Python: >= 3.4
Requires-Dist: urwid (>=2.0.0)
Requires-Dist: additional-urwid-widgets (==0.4.1)
Requires-Dist: pyperclip (>=1.7.0)
